miguxes_py/__init__.py
miguxes_py/dialetos.py
miguxes_py/miguxes.py
miguxespy-1.0.3.dist-info/WHEEL
miguxespy-1.0.3.dist-info/METADATA
miguxespy-1.0.3.dist-info/RECORD
