Metadata-Version: 2.1
Name: miguxespy
Version: 1.0.3
Summary: Modulo que traduz português para miguxês e suas variações (arcaico, moderno e NEO-miguxês). Inspirado no projeto de Aurelio Jargas, que pode ser encontrado em: https://aurelio.net/coisinha/miguxeitor
Home-page: https://github.com/matheuszinn/miguxes_py
Keywords: emo,miguxes,RegEx,brasil,meme
Author: Matheus Alves
Author-email: theustloz@gmail.com
Requires-Python: >=3.7,<4.0
Classifier: Programming Language :: Python :: 3
Classifier: Programming Language :: Python :: 3.7
Classifier: Programming Language :: Python :: 3.8
Classifier: Programming Language :: Python :: 3.9
Classifier: Programming Language :: Python :: 3.10
Classifier: Programming Language :: Python :: 3.11
Project-URL: Repository, https://github.com/matheuszinn/miguxes_py
